PikaChewie-1.3.0.dist-info/DESCRIPTION.rst
PikaChewie-1.3.0.dist-info/METADATA
PikaChewie-1.3.0.dist-info/RECORD
PikaChewie-1.3.0.dist-info/WHEEL
PikaChewie-1.3.0.dist-info/metadata.json
PikaChewie-1.3.0.dist-info/top_level.txt
pikachewie/__init__.py
pikachewie/agent.py
pikachewie/broker.py
pikachewie/consumer.py
pikachewie/data.py
pikachewie/exceptions.py
pikachewie/helpers.py
pikachewie/message.py
pikachewie/publisher.py
pikachewie/utils.py
