Metadata-Version: 2.0
Name: PikaChewie
Version: 1.3.0
Summary: A pika-based RabbitMQ publisher-consumer framework
Home-page: https://github.com/bdeeney/PikaChewie
Author: Bryan Deeney
Author-email: rennybot@pobox.com
License: BSD
Download-URL: https://github.com/bdeeney/PikaChewie/tarball/1.3.0
Platform: UNKNOWN
Classifier: Development Status :: 4 - Beta
Classifier: Intended Audience :: Developers
Classifier: License :: OSI Approved :: BSD License
Classifier: Natural Language :: English
Classifier: Operating System :: OS Independent
Classifier: Programming Language :: Python
Classifier: Programming Language :: Python :: 2
Classifier: Programming Language :: Python :: 2.6
Classifier: Programming Language :: Python :: 2.7
Classifier: Programming Language :: Python :: 3
Classifier: Programming Language :: Python :: 3.3
Classifier: Programming Language :: Python :: 3.4
Classifier: Topic :: Communications
Classifier: Topic :: Internet
Classifier: Topic :: Software Development :: Libraries
Classifier: Topic :: Software Development :: Libraries :: Python Modules
Requires-Dist: pika
Requires-Dist: simplejson
Requires-Dist: tornado
